Laboratorio_03/06.Tabla04 SOP/Tabla04SOP.v
  module Tabla04SOP();

  reg A, B, C, D;
  wire andA, andB, andC, andD, andE, andF, andG, notA, notB, notC, notD, out;

  or O1(out, andA, andB, andC, andD, andE, andF, andG);
  and Y1(andA, notA, notB, notC, notD);
  and Y2(andB, notA, notB, C, notD);
  and Y3(andC, notA, notB, C, D);
  and Y4(andD, notA, B, C, notD);
  and Y5(andE, notA, B, C, D);
  and Y6(andF, A, notB, notC, notD);
  and Y7(andG, A, notB, C, notD);
  not Y1(notA, A);
  not Y2(notB, B);
  not Y3(notC, C);
  not Y3(notD, D);


  initial begin
    $display("A B C D | Y");

    $monitor("%b %b %b %b | %b", A, B, C, D, out);
       A = 0; B = 0; C = 0; D= 0;
    #1 A = 0; B = 0; C = 0; D= 1;
    #1 A = 0; B = 0; C = 1; D= 0;
    #1 A = 0; B = 0; C = 1; D= 1;
    #1 A = 0; B = 1; C = 0; D= 0;
    #1 A = 0; B = 1; C = 0; D= 1;
    #1 A = 0; B = 1; C = 1; D= 0;
    #1 A = 0; B = 1; C = 1; D= 1;
    #1 A = 1; B = 0; C = 0; D= 0;
    #1 A = 1; B = 0; C = 0; D= 1;
    #1 A = 1; B = 0; C = 1; D= 0;
    #1 A = 1; B = 0; C = 1; D= 1;
    #1 A = 1; B = 1; C = 0; D= 0;
    #1 A = 1; B = 1; C = 0; D= 1;
    #1 A = 1; B = 1; C = 1; D= 0;
    #1 A = 1; B = 1; C = 1; D= 1;
    #1 $finish;
  end

  initial
    begin
      $dumpfile("Tabla04SOP_tb.vcd");
      $dumpvars(0,Tabla04SOP);
    end

endmodule

Laboratorio_03/06.Tabla04 SOP/Tabla04SOP_tb.vcd
$date
	Fri Jul 31 14:41:30 2020
$end
$version
	Icarus Verilog
$end
$timescale
	1ps
$end
$scope module Tabla04SOP $end
$var wire 1 ! andA $end
$var wire 1 " andB $end
$var wire 1 # andC $end
$var wire 1 $ andD $end
$var wire 1 % andE $end
$var wire 1 & andF $end
$var wire 1 ' andG $end
$var wire 1 ( notA $end
$var wire 1 ) notB $end
$var wire 1 * notC $end
$var wire 1 + notD $end
$var wire 1 , out $end
$var reg 1 - A $end
$var reg 1 . B $end
$var reg 1 / C $end
$var reg 1 0 D $end
$upscope $end
$enddefinitions $end
#0
$dumpvars
00
0/
0.
0-
1,
1+
1*
1)
1(
0'
0&
0%
0$
0#
0"
1!
$end
#1
0,
0!
0+
10
#2
1,
1"
1+
0*
00
1/
#3
0"
0+
1#
10
#4
0,
1+
1*
0#
0)
00
0/
1.
#5
0+
10
#6
1,
1$
1+
0*
00
1/
#7
0$
0+
1%
10
#8
1,
1&
1+
1*
1)
0%
0(
00
0/
0.
1-
#9
0,
0&
0+
10
#10
1,
1'
1+
0*
00
1/
#11
0,
0'
0+
10
#12
1+
1*
0)
00
0/
1.
#13
0+
10
#14
1+
0*
00
1/
#15
0+
10
