Laboratorio_05/Muxes.v

module MUX2_1(input wire s, d0, d1, output wire Y);
    assign Y = s ? d1 : d0;
endmodule


module MUX4_1(input wire d0, d1, d2, d3, input wire[1:0]s1, output wire Y);
  wire Y1, Y2;

  MUX2_1 M1(s1[0], d0, d1, Y1);
  MUX2_1 M2(s1[0], d2, d3, Y2);
  MUX2_1 M3(s1[1], Y1, Y2, Y);
endmodule


module MUX8_1(input wire d0, d1, d2, d3, d4, d5, d6, d7, input wire [2:0]s1, output wire Y);
  wire Y1, Y2;

  MUX4_1 M1(d0, d1, d2, d3, s1[1:0], Y1);
  MUX4_1 M2(d4, d5, d6, d7, s1[1:0], Y2);
  MUX2_1 M3(s1[2], Y1, Y2, Y);
endmodule


module Tabla1_MUX2_1(input wire A, B, C, output wire Y);
  assign Y1 = (B ^ C);
  assign Y2 = ~(B ^ C);
  MUX2_1 M1(A, Y1, Y2, Y);
endmodule


module Tabla1_MUX4_2(input wire A, B, C, output wire Y);
  wire Y1;
  wire [1:0]s1;
  assign Y1 = ~C;
  assign s1[0] = B;
  assign s1[1] = A;
  MUX4_1 M1(C, ~C, ~C, C, s1[1:0], Y);
endmodule


module Tabla1_MUX8_3(input wire A, B, C, Vcc, GND, output wire Y);
  wire [2:0]s1;
  assign s1[0] = C;
  assign s1[1] = B;
  assign s1[2] = A;
  MUX8_1 m1(GND, Vcc, Vcc, GND, Vcc, GND, GND, Vcc, s1[2:0], Y);
endmodule


module Tabla2_MUX2_1(input wire A, B, C, output wire Y);
  assign Y1 = (B ~| C);
  assign Y2 = ~(B & C);
  MUX2_1 M1(A, Y1, Y2, Y);
endmodule


module Tabla2_MUX4_2(input wire A, B, C, Vcc, GND, output wire Y);
  wire [1:0]s1;
  assign s1[0] = B;
  assign s1[1] = A;
  MUX4_1 M1(~C, GND, Vcc, ~C, s1[1:0], Y);
endmodule


module Tabla2_MUX8_3(input wire A, B, C, Vcc, GND, output wire Y);
  wire[2:0]s1;
  assign s1[0] = C;
  assign s1[1] = B;
  assign s1[2] = A;
  MUX8_1 M1(Vcc, GND, GND, GND, Vcc, Vcc, Vcc, GND, s1[2:0], Y);
endmodule

Laboratorio_05/Muxes_tb.v
module testbench();

reg p1, p2, p3;
wire Y1, Y2, Y3, Y4, Y5, Y6;
wire Vcc, GND;
assign Vcc = 1;
assign GND = 0;

Tabla1_MUX2_1 M1(p1, p2, p3, Y1);
Tabla1_MUX4_2 M2(p1, p2, p3, Y2);
Tabla1_MUX8_3 M3(p1, p2, p3, Vcc, GND, Y3);
Tabla2_MUX2_1 M4(p1, p2, p3, Y4);
Tabla2_MUX4_2 M5(p1, p2, p3, Vcc, GND, Y5);
Tabla2_MUX8_3 M6(p1, p2, p3, Vcc, GND, Y6);

initial begin
  $display("Tabla 1 MUX 2:1");
  $display("A B C | Y");
  $display("------|--");
  $monitor("%b %b %b | %b", p1, p2, p3, Y1);
      p1 = 0; p2 = 0; p3 = 0;
    #1 p1 = 0; p2 = 0; p3 = 1;
    #1 p1 = 0; p2 = 1; p3 = 0;
    #1 p1 = 0; p2 = 1; p3 = 1;
    #1 p1 = 1; p2 = 0; p3 = 0;
    #1 p1 = 1; p2 = 0; p3 = 1;
    #1 p1 = 1; p2 = 1; p3 = 0;
    #1 p1 = 1; p2 = 1; p3 = 1;
end

initial begin
  #8
  $display("\n");
  $display("Tabla 1 MUX 4:1");
  $display("A B C | Y");
  $display("------|--");
  $monitor("%b %b %b | %b", p1, p2, p3, Y2);
      p1 = 0; p2 = 0; p3 = 0;
    #1 p1 = 0; p2 = 0; p3 = 1;
    #1 p1 = 0; p2 = 1; p3 = 0;
    #1 p1 = 0; p2 = 1; p3 = 1;
    #1 p1 = 1; p2 = 0; p3 = 0;
    #1 p1 = 1; p2 = 0; p3 = 1;
    #1 p1 = 1; p2 = 1; p3 = 0;
    #1 p1 = 1; p2 = 1; p3 = 1;
end

initial begin
  #16
  $display("\n");
  $display("Tabla 1 MUX 8:1");
  $display("A B C | Y");
  $display("------|--");
  $monitor("%b %b %b | %b", p1, p2, p3, Y3);
      p1 = 0; p2 = 0; p3 = 0;
    #1 p1 = 0; p2 = 0; p3 = 1;
    #1 p1 = 0; p2 = 1; p3 = 0;
    #1 p1 = 0; p2 = 1; p3 = 1;
    #1 p1 = 1; p2 = 0; p3 = 0;
    #1 p1 = 1; p2 = 0; p3 = 1;
    #1 p1 = 1; p2 = 1; p3 = 0;
    #1 p1 = 1; p2 = 1; p3 = 1;
end

initial begin
  #24
  $display("\n");
  $display("Tabla 2 MUX 2:1");
  $display("A B C | Y");
  $display("------|--");
  $monitor("%b %b %b | %b", p1, p2, p3, Y4);
      p1 = 0; p2 = 0; p3 = 0;
    #1 p1 = 0; p2 = 0; p3 = 1;
    #1 p1 = 0; p2 = 1; p3 = 0;
    #1 p1 = 0; p2 = 1; p3 = 1;
    #1 p1 = 1; p2 = 0; p3 = 0;
    #1 p1 = 1; p2 = 0; p3 = 1;
    #1 p1 = 1; p2 = 1; p3 = 0;
    #1 p1 = 1; p2 = 1; p3 = 1;
end

initial begin
  #32
  $display("\n");
  $display("Tabla 2 MUX 4:1");
  $display("A B C | Y");
  $display("------|--");
  $monitor("%b %b %b | %b", p1, p2, p3, Y5);
      p1 = 0; p2 = 0; p3 = 0;
    #1 p1 = 0; p2 = 0; p3 = 1;
    #1 p1 = 0; p2 = 1; p3 = 0;
    #1 p1 = 0; p2 = 1; p3 = 1;
    #1 p1 = 1; p2 = 0; p3 = 0;
    #1 p1 = 1; p2 = 0; p3 = 1;
    #1 p1 = 1; p2 = 1; p3 = 0;
    #1 p1 = 1; p2 = 1; p3 = 1;
end

initial begin
  #40
  $display("\n");
  $display("Tabla 2 MUX 8:1");
  $display("A B C | Y");
  $display("------|--");
  $monitor("%b %b %b | %b", p1, p2, p3, Y6);
      p1 = 0; p2 = 0; p3 = 0;
    #1 p1 = 0; p2 = 0; p3 = 1;
    #1 p1 = 0; p2 = 1; p3 = 0;
    #1 p1 = 0; p2 = 1; p3 = 1;
    #1 p1 = 1; p2 = 0; p3 = 0;
    #1 p1 = 1; p2 = 0; p3 = 1;
    #1 p1 = 1; p2 = 1; p3 = 0;
    #1 p1 = 1; p2 = 1; p3 = 1;
end

initial
  #72 $finish;

initial begin
  $dumpfile("Muxes_tb.vcd");
  $dumpvars(0, testbench);
end

endmodule

Laboratorio_05/Muxes_tb.vcd
$date
	Sun Aug 16 02:17:23 2020
$end
$version
	Icarus Verilog
$end
$timescale
	1ps
$end
$scope module testbench $end
$var wire 1 ! GND $end
$var wire 1 " Vcc $end
$var wire 1 # Y6 $end
$var wire 1 $ Y5 $end
$var wire 1 % Y4 $end
$var wire 1 & Y3 $end
$var wire 1 ' Y2 $end
$var wire 1 ( Y1 $end
$var reg 1 ) p1 $end
$var reg 1 * p2 $end
$var reg 1 + p3 $end
$scope module M1 $end
$var wire 1 ) A $end
$var wire 1 * B $end
$var wire 1 + C $end
$var wire 1 , Y1 $end
$var wire 1 - Y2 $end
$var wire 1 ( Y $end
$scope module M1 $end
$var wire 1 , d0 $end
$var wire 1 - d1 $end
$var wire 1 ) s $end
$var wire 1 ( Y $end
$upscope $end
$upscope $end
$scope module M2 $end
$var wire 1 ) A $end
$var wire 1 * B $end
$var wire 1 + C $end
$var wire 1 . Y1 $end
$var wire 2 / s1 [1:0] $end
$var wire 1 ' Y $end
$scope module M1 $end
$var wire 1 + d0 $end
$var wire 1 0 d1 $end
$var wire 1 1 d2 $end
$var wire 1 + d3 $end
$var wire 2 2 s1 [1:0] $end
$var wire 1 3 Y2 $end
$var wire 1 4 Y1 $end
$var wire 1 ' Y $end
$scope module M1 $end
$var wire 1 + d0 $end
$var wire 1 0 d1 $end
$var wire 1 5 s $end
$var wire 1 4 Y $end
$upscope $end
$scope module M2 $end
$var wire 1 1 d0 $end
$var wire 1 + d1 $end
$var wire 1 6 s $end
$var wire 1 3 Y $end
$upscope $end
$scope module M3 $end
$var wire 1 4 d0 $end
$var wire 1 3 d1 $end
$var wire 1 7 s $end
$var wire 1 ' Y $end
$upscope $end
$upscope $end
$upscope $end
$scope module M3 $end
$var wire 1 ) A $end
$var wire 1 * B $end
$var wire 1 + C $end
$var wire 1 ! GND $end
$var wire 1 " Vcc $end
$var wire 3 8 s1 [2:0] $end
$var wire 1 & Y $end
$scope module m1 $end
$var wire 1 ! d0 $end
$var wire 1 " d1 $end
$var wire 1 " d2 $end
$var wire 1 ! d3 $end
$var wire 1 " d4 $end
$var wire 1 ! d5 $end
$var wire 1 ! d6 $end
$var wire 1 " d7 $end
$var wire 3 9 s1 [2:0] $end
$var wire 1 : Y2 $end
$var wire 1 ; Y1 $end
$var wire 1 & Y $end
$scope module M1 $end
$var wire 1 ! d0 $end
$var wire 1 " d1 $end
$var wire 1 " d2 $end
$var wire 1 ! d3 $end
$var wire 2 < s1 [1:0] $end
$var wire 1 = Y2 $end
$var wire 1 > Y1 $end
$var wire 1 ; Y $end
$scope module M1 $end
$var wire 1 ! d0 $end
$var wire 1 " d1 $end
$var wire 1 ? s $end
$var wire 1 > Y $end
$upscope $end
$scope module M2 $end
$var wire 1 " d0 $end
$var wire 1 ! d1 $end
$var wire 1 @ s $end
$var wire 1 = Y $end
$upscope $end
$scope module M3 $end
$var wire 1 > d0 $end
$var wire 1 = d1 $end
$var wire 1 A s $end
$var wire 1 ; Y $end
$upscope $end
$upscope $end
$scope module M2 $end
$var wire 1 " d0 $end
$var wire 1 ! d1 $end
$var wire 1 ! d2 $end
$var wire 1 " d3 $end
$var wire 2 B s1 [1:0] $end
$var wire 1 C Y2 $end
$var wire 1 D Y1 $end
$var wire 1 : Y $end
$scope module M1 $end
$var wire 1 " d0 $end
$var wire 1 ! d1 $end
$var wire 1 E s $end
$var wire 1 D Y $end
$upscope $end
$scope module M2 $end
$var wire 1 ! d0 $end
$var wire 1 " d1 $end
$var wire 1 F s $end
$var wire 1 C Y $end
$upscope $end
$scope module M3 $end
$var wire 1 D d0 $end
$var wire 1 C d1 $end
$var wire 1 G s $end
$var wire 1 : Y $end
$upscope $end
$upscope $end
$scope module M3 $end
$var wire 1 ; d0 $end
$var wire 1 : d1 $end
$var wire 1 H s $end
$var wire 1 & Y $end
$upscope $end
$upscope $end
$upscope $end
$scope module M4 $end
$var wire 1 ) A $end
$var wire 1 * B $end
$var wire 1 + C $end
$var wire 1 I Y1 $end
$var wire 1 J Y2 $end
$var wire 1 % Y $end
$scope module M1 $end
$var wire 1 I d0 $end
$var wire 1 J d1 $end
$var wire 1 ) s $end
$var wire 1 % Y $end
$upscope $end
$upscope $end
$scope module M5 $end
$var wire 1 ) A $end
$var wire 1 * B $end
$var wire 1 + C $end
$var wire 1 ! GND $end
$var wire 1 " Vcc $end
$var wire 2 K s1 [1:0] $end
$var wire 1 $ Y $end
$scope module M1 $end
$var wire 1 L d0 $end
$var wire 1 ! d1 $end
$var wire 1 " d2 $end
$var wire 1 M d3 $end
$var wire 2 N s1 [1:0] $end
$var wire 1 O Y2 $end
$var wire 1 P Y1 $end
$var wire 1 $ Y $end
$scope module M1 $end
$var wire 1 L d0 $end
$var wire 1 ! d1 $end
$var wire 1 Q s $end
$var wire 1 P Y $end
$upscope $end
$scope module M2 $end
$var wire 1 " d0 $end
$var wire 1 M d1 $end
$var wire 1 R s $end
$var wire 1 O Y $end
$upscope $end
$scope module M3 $end
$var wire 1 P d0 $end
$var wire 1 O d1 $end
$var wire 1 S s $end
$var wire 1 $ Y $end
$upscope $end
$upscope $end
$upscope $end
$scope module M6 $end
$var wire 1 ) A $end
$var wire 1 * B $end
$var wire 1 + C $end
$var wire 1 ! GND $end
$var wire 1 " Vcc $end
$var wire 3 T s1 [2:0] $end
$var wire 1 # Y $end
$scope module M1 $end
$var wire 1 " d0 $end
$var wire 1 ! d1 $end
$var wire 1 ! d2 $end
$var wire 1 ! d3 $end
$var wire 1 " d4 $end
$var wire 1 " d5 $end
$var wire 1 " d6 $end
$var wire 1 ! d7 $end
$var wire 3 U s1 [2:0] $end
$var wire 1 V Y2 $end
$var wire 1 W Y1 $end
$var wire 1 # Y $end
$scope module M1 $end
$var wire 1 " d0 $end
$var wire 1 ! d1 $end
$var wire 1 ! d2 $end
$var wire 1 ! d3 $end
$var wire 2 X s1 [1:0] $end
$var wire 1 Y Y2 $end
$var wire 1 Z Y1 $end
$var wire 1 W Y $end
$scope module M1 $end
$var wire 1 " d0 $end
$var wire 1 ! d1 $end
$var wire 1 [ s $end
$var wire 1 Z Y $end
$upscope $end
$scope module M2 $end
$var wire 1 ! d0 $end
$var wire 1 ! d1 $end
$var wire 1 \ s $end
$var wire 1 Y Y $end
$upscope $end
$scope module M3 $end
$var wire 1 Z d0 $end
$var wire 1 Y d1 $end
$var wire 1 ] s $end
$var wire 1 W Y $end
$upscope $end
$upscope $end
$scope module M2 $end
$var wire 1 " d0 $end
$var wire 1 " d1 $end
$var wire 1 " d2 $end
$var wire 1 ! d3 $end
$var wire 2 ^ s1 [1:0] $end
$var wire 1 _ Y2 $end
$var wire 1 ` Y1 $end
$var wire 1 V Y $end
$scope module M1 $end
$var wire 1 " d0 $end
$var wire 1 " d1 $end
$var wire 1 a s $end
$var wire 1 ` Y $end
$upscope $end
$scope module M2 $end
$var wire 1 " d0 $end
$var wire 1 ! d1 $end
$var wire 1 b s $end
$var wire 1 _ Y $end
$upscope $end
$scope module M3 $end
$var wire 1 ` d0 $end
$var wire 1 _ d1 $end
$var wire 1 c s $end
$var wire 1 V Y $end
$upscope $end
$upscope $end
$scope module M3 $end
$var wire 1 W d0 $end
$var wire 1 V d1 $end
$var wire 1 d s $end
$var wire 1 # Y $end
$upscope $end
$upscope $end
$upscope $end
$upscope $end
$enddefinitions $end
#0
$dumpvars
0d
0c
0b
0a
1`
1_
b0 ^
0]
0\
0[
1Z
0Y
b0 X
1W
1V
b0 U
b0 T
0S
0R
0Q
1P
1O
b0 N
1M
1L
b0 K
1J
1I
0H
0G
0F
0E
1D
0C
b0 B
0A
0@
0?
0>
1=
b0 <
0;
1:
b0 9
b0 8
07
06
05
04
13
b0 2
11
10
b0 /
1.
1-
0,
0+
0*
0)
0(
0'
0&
1%
1$
1#
1"
0!
$end
#1
1&
0#
1;
0:
0W
1>
0=
0D
1C
0$
0Z
0_
1(
0-
03
1'
1?
1@
1E
1F
0%
0P
1[
1\
1a
1b
1,
0.
00
01
14
b1 <
b1 B
0I
0L
0M
b1 X
b1 ^
b1 8
b1 9
b1 T
b1 U
1+
#2
1&
0>
1=
1;
1D
0C
0:
1Z
1_
1V
1'
0?
0@
1A
0E
0F
1G
0[
0\
1]
0a
0b
1c
1.
10
11
14
1L
1M
15
16
b10 <
b10 B
1Q
1R
b10 X
b10 ^
0+
b1 /
b1 2
b10 8
b10 9
b1 K
b1 N
b10 T
b10 U
1*
#3
0&
0;
1:
0V
0'
1>
0=
0D
1C
0Z
0_
0(
1-
04
1?
1@
1E
1F
0J
0O
1[
1\
1a
1b
0,
0.
00
01
13
b11 <
b11 B
0L
0M
b11 X
b11 ^
b11 8
b11 9
b11 T
b11 U
1+
#4
1W
1#
1'
0>
1=
0;
1D
0C
1:
1%
1$
1Z
1_
1V
0?
0@
0A
0E
0F
0G
1J
1P
1O
0[
0\
0]
0a
0b
0c
1&
1.
10
11
13
1L
1M
05
06
b0 <
b0 B
1I
0Q
0R
b0 X
b0 ^
1(
17
1H
1S
1d
0+
0*
b10 /
b10 2
b100 8
b100 9
b10 K
b10 N
b100 T
b100 U
1)
#5
0&
1;
0:
0W
0(
0'
1>
0=
0D
1C
0Z
0_
0-
03
1?
1@
1E
1F
0P
1[
1\
1a
1b
1,
0.
00
01
14
b1 <
b1 B
0I
0L
0M
b1 X
b1 ^
b101 8
b101 9
b101 T
b101 U
1+
#6
0&
1#
0>
1=
1;
1D
0C
0:
1Z
1_
1V
0?
0@
1A
0E
0F
1G
0[
0\
1]
0a
0b
1c
1.
10
11
14
1L
1M
15
16
b10 <
b10 B
1Q
1R
b10 X
b10 ^
0+
b11 /
b11 2
b110 8
b110 9
b11 K
b11 N
b110 T
b110 U
1*
#7
1&
0#
0;
1:
0V
1(
1>
0=
0D
1C
0%
0$
0Z
0_
1-
04
1'
1?
1@
1E
1F
0J
0O
1[
1\
1a
1b
0,
0.
00
01
13
b11 <
b11 B
0L
0M
b11 X
b11 ^
b111 8
b111 9
b111 T
b111 U
1+
#8
1#
1W
0>
1=
0;
1D
0C
1:
1$
1Z
1_
1V
0?
0@
0A
0E
0F
0G
1%
1J
1P
1O
0[
0\
0]
0a
0b
0c
0'
0&
1.
10
11
13
1L
1M
05
06
b0 <
b0 B
1I
0Q
0R
b0 X
b0 ^
0(
07
0H
0S
0d
0+
0*
b0 /
b0 2
b0 8
b0 9
b0 K
b0 N
b0 T
b0 U
0)
#9
1&
0#
1;
0:
0W
1>
0=
0D
1C
0$
0Z
0_
1(
0-
03
1'
1?
1@
1E
1F
0%
0P
1[
1\
1a
1b
1,
0.
00
01
14
b1 <
b1 B
0I
0L
0M
b1 X
b1 ^
b1 8
b1 9
b1 T
b1 U
1+
#10
1&
0>
1=
1;
1D
0C
0:
1Z
1_
1V
1'
0?
0@
1A
0E
0F
1G
0[
0\
1]
0a
0b
1c
1.
10
11
14
1L
1M
15
16
b10 <
b10 B
1Q
1R
b10 X
b10 ^
0+
b1 /
b1 2
b10 8
b10 9
b1 K
b1 N
b10 T
b10 U
1*
#11
0&
0;
1:
0V
0'
1>
0=
0D
1C
0Z
0_
0(
1-
04
1?
1@
1E
1F
0J
0O
1[
1\
1a
1b
0,
0.
00
01
13
b11 <
b11 B
0L
0M
b11 X
b11 ^
b11 8
b11 9
b11 T
b11 U
1+
#12
1W
1#
1'
0>
1=
0;
1D
0C
1:
1%
1$
1Z
1_
1V
0?
0@
0A
0E
0F
0G
1J
1P
1O
0[
0\
0]
0a
0b
0c
1&
1.
10
11
13
1L
1M
05
06
b0 <
b0 B
1I
0Q
0R
b0 X
b0 ^
1(
17
1H
1S
1d
0+
0*
b10 /
b10 2
b100 8
b100 9
b10 K
b10 N
b100 T
b100 U
1)
#13
0&
1;
0:
0W
0(
0'
1>
0=
0D
1C
0Z
0_
0-
03
1?
1@
1E
1F
0P
1[
1\
1a
1b
1,
0.
00
01
14
b1 <
b1 B
0I
0L
0M
b1 X
b1 ^
b101 8
b101 9
b101 T
b101 U
1+
#14
0&
1#
0>
1=
1;
1D
0C
0:
1Z
1_
1V
0?
0@
1A
0E
0F
1G
0[
0\
1]
0a
0b
1c
1.
10
11
14
1L
1M
15
16
b10 <
b10 B
1Q
1R
b10 X
b10 ^
0+
b11 /
b11 2
b110 8
b110 9
b11 K
b11 N
b110 T
b110 U
1*
#15
1&
0#
0;
1:
0V
1(
1>
0=
0D
1C
0%
0$
0Z
0_
1-
04
1'
1?
1@
1E
1F
0J
0O
1[
1\
1a
1b
0,
0.
00
01
13
b11 <
b11 B
0L
0M
b11 X
b11 ^
b111 8
b111 9
b111 T
b111 U
1+
#16
1#
1W
0>
1=
0;
1D
0C
1:
1$
1Z
1_
1V
0?
0@
0A
0E
0F
0G
1%
1J
1P
1O
0[
0\
0]
0a
0b
0c
0'
0&
1.
10
11
13
1L
1M
05
06
b0 <
b0 B
1I
0Q
0R
b0 X
b0 ^
0(
07
0H
0S
0d
0+
0*
b0 /
b0 2
b0 8
b0 9
b0 K
b0 N
b0 T
b0 U
0)
#17
1&
0#
1;
0:
0W
1>
0=
0D
1C
0$
0Z
0_
1(
0-
03
1'
1?
1@
1E
1F
0%
0P
1[
1\
1a
1b
1,
0.
00
01
14
b1 <
b1 B
0I
0L
0M
b1 X
b1 ^
b1 8
b1 9
b1 T
b1 U
1+
#18
1&
0>
1=
1;
1D
0C
0:
1Z
1_
1V
1'
0?
0@
1A
0E
0F
1G
0[
0\
1]
0a
0b
1c
1.
10
11
14
1L
1M
15
16
b10 <
b10 B
1Q
1R
b10 X
b10 ^
0+
b1 /
b1 2
b10 8
b10 9
b1 K
b1 N
b10 T
b10 U
1*
#19
0&
0;
1:
0V
0'
1>
0=
0D
1C
0Z
0_
0(
1-
04
1?
1@
1E
1F
0J
0O
1[
1\
1a
1b
0,
0.
00
01
13
b11 <
b11 B
0L
0M
b11 X
b11 ^
b11 8
b11 9
b11 T
b11 U
1+
#20
1W
1#
1'
0>
1=
0;
1D
0C
1:
1%
1$
1Z
1_
1V
0?
0@
0A
0E
0F
0G
1J
1P
1O
0[
0\
0]
0a
0b
0c
1&
1.
10
11
13
1L
1M
05
06
b0 <
b0 B
1I
0Q
0R
b0 X
b0 ^
1(
17
1H
1S
1d
0+
0*
b10 /
b10 2
b100 8
b100 9
b10 K
b10 N
b100 T
b100 U
1)
#21
0&
1;
0:
0W
0(
0'
1>
0=
0D
1C
0Z
0_
0-
03
1?
1@
1E
1F
0P
1[
1\
1a
1b
1,
0.
00
01
14
b1 <
b1 B
0I
0L
0M
b1 X
b1 ^
b101 8
b101 9
b101 T
b101 U
1+
#22
0&
1#
0>
1=
1;
1D
0C
0:
1Z
1_
1V
0?
0@
1A
0E
0F
1G
0[
0\
1]
0a
0b
1c
1.
10
11
14
1L
1M
15
16
b10 <
b10 B
1Q
1R
b10 X
b10 ^
0+
b11 /
b11 2
b110 8
b110 9
b11 K
b11 N
b110 T
b110 U
1*
#23
1&
0#
0;
1:
0V
1(
1>
0=
0D
1C
0%
0$
0Z
0_
1-
04
1'
1?
1@
1E
1F
0J
0O
1[
1\
1a
1b
0,
0.
00
01
13
b11 <
b11 B
0L
0M
b11 X
b11 ^
b111 8
b111 9
b111 T
b111 U
1+
#24
1#
1W
0>
1=
0;
1D
0C
1:
1$
1Z
1_
1V
0?
0@
0A
0E
0F
0G
1%
1J
1P
1O
0[
0\
0]
0a
0b
0c
0'
0&
1.
10
11
13
1L
1M
05
06
b0 <
b0 B
1I
0Q
0R
b0 X
b0 ^
0(
07
0H
0S
0d
0+
0*
b0 /
b0 2
b0 8
b0 9
b0 K
b0 N
b0 T
b0 U
0)
#25
1&
0#
1;
0:
0W
1>
0=
0D
1C
0$
0Z
0_
1(
0-
03
1'
1?
1@
1E
1F
0%
0P
1[
1\
1a
1b
1,
0.
00
01
14
b1 <
b1 B
0I
0L
0M
b1 X
b1 ^
b1 8
b1 9
b1 T
b1 U
1+
#26
1&
0>
1=
1;
1D
0C
0:
1Z
1_
1V
1'
0?
0@
1A
0E
0F
1G
0[
0\
1]
0a
0b
1c
1.
10
11
14
1L
1M
15
16
b10 <
b10 B
1Q
1R
b10 X
b10 ^
0+
b1 /
b1 2
b10 8
b10 9
b1 K
b1 N
b10 T
b10 U
1*
#27
0&
0;
1:
0V
0'
1>
0=
0D
1C
0Z
0_
0(
1-
04
1?
1@
1E
1F
0J
0O
1[
1\
1a
1b
0,
0.
00
01
13
b11 <
b11 B
0L
0M
b11 X
b11 ^
b11 8
b11 9
b11 T
b11 U
1+
#28
1W
1#
1'
0>
1=
0;
1D
0C
1:
1%
1$
1Z
1_
1V
0?
0@
0A
0E
0F
0G
1J
1P
1O
0[
0\
0]
0a
0b
0c
1&
1.
10
11
13
1L
1M
05
06
b0 <
b0 B
1I
0Q
0R
b0 X
b0 ^
1(
17
1H
1S
1d
0+
0*
b10 /
b10 2
b100 8
b100 9
b10 K
b10 N
b100 T
b100 U
1)
#29
0&
1;
0:
0W
0(
0'
1>
0=
0D
1C
0Z
0_
0-
03
1?
1@
1E
1F
0P
1[
1\
1a
1b
1,
0.
00
01
14
b1 <
b1 B
0I
0L
0M
b1 X
b1 ^
b101 8
b101 9
b101 T
b101 U
1+
#30
0&
1#
0>
1=
1;
1D
0C
0:
1Z
1_
1V
0?
0@
1A
0E
0F
1G
0[
0\
1]
0a
0b
1c
1.
10
11
14
1L
1M
15
16
b10 <
b10 B
1Q
1R
b10 X
b10 ^
0+
b11 /
b11 2
b110 8
b110 9
b11 K
b11 N
b110 T
b110 U
1*
#31
1&
0#
0;
1:
0V
1(
1>
0=
0D
1C
0%
0$
0Z
0_
1-
04
1'
1?
1@
1E
1F
0J
0O
1[
1\
1a
1b
0,
0.
00
01
13
b11 <
b11 B
0L
0M
b11 X
b11 ^
b111 8
b111 9
b111 T
b111 U
1+
#32
1#
1W
0>
1=
0;
1D
0C
1:
1$
1Z
1_
1V
0?
0@
0A
0E
0F
0G
1%
1J
1P
1O
0[
0\
0]
0a
0b
0c
0'
0&
1.
10
11
13
1L
1M
05
06
b0 <
b0 B
1I
0Q
0R
b0 X
b0 ^
0(
07
0H
0S
0d
0+
0*
b0 /
b0 2
b0 8
b0 9
b0 K
b0 N
b0 T
b0 U
0)
#33
1&
0#
1;
0:
0W
1>
0=
0D
1C
0$
0Z
0_
1(
0-
03
1'
1?
1@
1E
1F
0%
0P
1[
1\
1a
1b
1,
0.
00
01
14
b1 <
b1 B
0I
0L
0M
b1 X
b1 ^
b1 8
b1 9
b1 T
b1 U
1+
#34
1&
0>
1=
1;
1D
0C
0:
1Z
1_
1V
1'
0?
0@
1A
0E
0F
1G
0[
0\
1]
0a
0b
1c
1.
10
11
14
1L
1M
15
16
b10 <
b10 B
1Q
1R
b10 X
b10 ^
0+
b1 /
b1 2
b10 8
b10 9
b1 K
b1 N
b10 T
b10 U
1*
#35
0&
0;
1:
0V
0'
1>
0=
0D
1C
0Z
0_
0(
1-
04
1?
1@
1E
1F
0J
0O
1[
1\
1a
1b
0,
0.
00
01
13
b11 <
b11 B
0L
0M
b11 X
b11 ^
b11 8
b11 9
b11 T
b11 U
1+
#36
1W
1#
1'
0>
1=
0;
1D
0C
1:
1%
1$
1Z
1_
1V
0?
0@
0A
0E
0F
0G
1J
1P
1O
0[
0\
0]
0a
0b
0c
1&
1.
10
11
13
1L
1M
05
06
b0 <
b0 B
1I
0Q
0R
b0 X
b0 ^
1(
17
1H
1S
1d
0+
0*
b10 /
b10 2
b100 8
b100 9
b10 K
b10 N
b100 T
b100 U
1)
#37
0&
1;
0:
0W
0(
0'
1>
0=
0D
1C
0Z
0_
0-
03
1?
1@
1E
1F
0P
1[
1\
1a
1b
1,
0.
00
01
14
b1 <
b1 B
0I
0L
0M
b1 X
b1 ^
b101 8
b101 9
b101 T
b101 U
1+
#38
0&
1#
0>
1=
1;
1D
0C
0:
1Z
1_
1V
0?
0@
1A
0E
0F
1G
0[
0\
1]
0a
0b
1c
1.
10
11
14
1L
1M
15
16
b10 <
b10 B
1Q
1R
b10 X
b10 ^
0+
b11 /
b11 2
b110 8
b110 9
b11 K
b11 N
b110 T
b110 U
1*
#39
1&
0#
0;
1:
0V
1(
1>
0=
0D
1C
0%
0$
0Z
0_
1-
04
1'
1?
1@
1E
1F
0J
0O
1[
1\
1a
1b
0,
0.
00
01
13
b11 <
b11 B
0L
0M
b11 X
b11 ^
b111 8
b111 9
b111 T
b111 U
1+
#40
1#
1W
0>
1=
0;
1D
0C
1:
1$
1Z
1_
1V
0?
0@
0A
0E
0F
0G
1%
1J
1P
1O
0[
0\
0]
0a
0b
0c
0'
0&
1.
10
11
13
1L
1M
05
06
b0 <
b0 B
1I
0Q
0R
b0 X
b0 ^
0(
07
0H
0S
0d
0+
0*
b0 /
b0 2
b0 8
b0 9
b0 K
b0 N
b0 T
b0 U
0)
#41
1&
0#
1;
0:
0W
1>
0=
0D
1C
0$
0Z
0_
1(
0-
03
1'
1?
1@
1E
1F
0%
0P
1[
1\
1a
1b
1,
0.
00
01
14
b1 <
b1 B
0I
0L
0M
b1 X
b1 ^
b1 8
b1 9
b1 T
b1 U
1+
#42
1&
0>
1=
1;
1D
0C
0:
1Z
1_
1V
1'
0?
0@
1A
0E
0F
1G
0[
0\
1]
0a
0b
1c
1.
10
11
14
1L
1M
15
16
b10 <
b10 B
1Q
1R
b10 X
b10 ^
0+
b1 /
b1 2
b10 8
b10 9
b1 K
b1 N
b10 T
b10 U
1*
#43
0&
0;
1:
0V
0'
1>
0=
0D
1C
0Z
0_
0(
1-
04
1?
1@
1E
1F
0J
0O
1[
1\
1a
1b
0,
0.
00
01
13
b11 <
b11 B
0L
0M
b11 X
b11 ^
b11 8
b11 9
b11 T
b11 U
1+
#44
1W
1#
1'
0>
1=
0;
1D
0C
1:
1%
1$
1Z
1_
1V
0?
0@
0A
0E
0F
0G
1J
1P
1O
0[
0\
0]
0a
0b
0c
1&
1.
10
11
13
1L
1M
05
06
b0 <
b0 B
1I
0Q
0R
b0 X
b0 ^
1(
17
1H
1S
1d
0+
0*
b10 /
b10 2
b100 8
b100 9
b10 K
b10 N
b100 T
b100 U
1)
#45
0&
1;
0:
0W
0(
0'
1>
0=
0D
1C
0Z
0_
0-
03
1?
1@
1E
1F
0P
1[
1\
1a
1b
1,
0.
00
01
14
b1 <
b1 B
0I
0L
0M
b1 X
b1 ^
b101 8
b101 9
b101 T
b101 U
1+
#46
0&
1#
0>
1=
1;
1D
0C
0:
1Z
1_
1V
0?
0@
1A
0E
0F
1G
0[
0\
1]
0a
0b
1c
1.
10
11
14
1L
1M
15
16
b10 <
b10 B
1Q
1R
b10 X
b10 ^
0+
b11 /
b11 2
b110 8
b110 9
b11 K
b11 N
b110 T
b110 U
1*
#47
1&
0#
0;
1:
0V
1(
1>
0=
0D
1C
0%
0$
0Z
0_
1-
04
1'
1?
1@
1E
1F
0J
0O
1[
1\
1a
1b
0,
0.
00
01
13
b11 <
b11 B
0L
0M
b11 X
b11 ^
b111 8
b111 9
b111 T
b111 U
1+
