Laboratorio_03/02.Tabla02 SOP/Tabla02SOP.v
  module Tabla02SOP();

  reg A, B, C;
  wire andA, andB, andC, notA, notB, notC, out;

  or  O1(out, andA, andB, andC);
  and Y1(andA, notA, notB, C);
  and Y2(andB, A, B, notC);
  and Y3(andC, A, B, C);
  not N1(notA, A);
  not N2(notB, B);
  not N3(notC, C);

  initial begin
    $display("A B C | Y");

    $monitor("%b %b %b | %b", A, B, C, out);
       A = 0; B = 0; C= 0;
    #1 A = 0; B = 0; C= 1;
    #1 A = 0; B = 1; C= 0;
    #1 A = 0; B = 1; C= 1;
    #1 A = 1; B = 0; C= 0;
    #1 A = 1; B = 0; C= 1;
    #1 A = 1; B = 1; C= 0;
    #1 A = 1; B = 1; C= 1;
    #1 $finish;
  end

  initial
    begin
      $dumpfile("Tabla02SOP_tb.vcd");
      $dumpvars(0,Tabla02SOP);
    end

endmodule

Laboratorio_03/02.Tabla02 SOP/Tabla02SOP_tb.vcd
$date
	Fri Jul 31 14:38:18 2020
$end
$version
	Icarus Verilog
$end
$timescale
	1ps
$end
$scope module Tabla02SOP $end
$var wire 1 ! andA $end
$var wire 1 " andB $end
$var wire 1 # andC $end
$var wire 1 $ notA $end
$var wire 1 % notB $end
$var wire 1 & notC $end
$var wire 1 ' out $end
$var reg 1 ( A $end
$var reg 1 ) B $end
$var reg 1 * C $end
$upscope $end
$enddefinitions $end
#0
$dumpvars
0*
0)
0(
0'
1&
1%
1$
0#
0"
0!
$end
#1
1'
0&
1!
1*
#2
0'
1&
0!
0%
0*
1)
#3
0&
1*
#4
1&
1%
0$
0*
0)
1(
#5
0&
1*
#6
1'
1"
1&
0%
0*
1)
#7
0"
0&
1#
1*
