Laboratorio_04/Ejercicio05/Alarma.v
module SOP01 (input wire A, B, C, output wire Y);   //Behavioral Modelling de SOP
  assign Y = (~A & ~B & ~C) | (~A & ~B & C) | (~A & B & ~C) |(~A & B & C) | (A & ~B & ~C) | (A & ~B & C) | (A & B & C);
endmodule

module POS01 (input wire A, B, C, output wire Y);   //Behavioral Modelling de POS
  assign Y = ~A | ~B | C;
endmodule

module MapaK01 (input wire A, B, C, output wire Y);   //Behavioral Modelling de MapaK
  assign Y = ~A | ~B | C;
endmodule

module SOP02 (input wire A, B, C, output wire Y);   //Gate Level Modelling de SOP
  wire notB;
  or  O1(Y, andA, andB, andC, andD, andE, andF, andG);
  and A1(andA, notA, notB, notC);
  and A2(andB, notA, notB, C);
  and A3(andC, notA, B, notC);
  and A4(andD, notA, B, C);
  and A5(andE, A, notB, notC);
  and A6(andF, A, notB, C);
  and A7(andG, A, B, C);
  not N1(notA, A);
  not N2(notB, B);
  not N3(notC, C);
endmodule

module POS02 (input wire A, B, C, output wire Y);    //Gate Level Modelling de POS
  or  O1(Y, notA, notB, C);
  not N1(notA, A);
  not N2(notB, B);
endmodule

module MapaK02 (input wire A, B, C, output wire Y);   //Gate Level Modelling de MapaK
  or  O1(Y, notA, notB, C);
  not N1(notA, A);
  not N2(notB, B);
endmodule

Laboratorio_04/Ejercicio05/Alarma_tb.v
module testbench();

  reg p1, p2, p3, p4, p5, p6, p7, p8, p9, p10, p11, p12, p13, p14, p15, p16, p17, p18;
  wire out1, out2, out3, out4, out5, out6;

  SOP01  SO1(p1, p2, p3, out1);  //Behavioral Modelling de SOP
  POS01  PO1(p4, p5, p6, out2);  //Behavioral Modelling de POS
  MapaK01  MK1(p7, p8, p9, out3);  //Behavioral Modelling de MapaK
  SOP02  SO2(p10, p11, p12, out4);  //Gate Level Modelling de SOP
  POS02  PO2(p13, p14, p15, out5);  //Gate Level Modelling de POS
  MapaK02  MK2(p16, p17, p18, out6);  //Gate Level Modelling de MapaK

 initial begin
   $display("A B C | Y");
   $display("------|--");
   $monitor("%b %b %b | %b", p1, p2, p3, out1);
        p1 = 0; p2 = 0; p3 = 0;
     #1 p1 = 0; p2 = 0; p3 = 1;
     #1 p1 = 0; p2 = 1; p3 = 0;
     #1 p1 = 0; p2 = 1; p3 = 1;
     #1 p1 = 1; p2 = 0; p3 = 0;
     #1 p1 = 1; p2 = 0; p3 = 1;
     #1 p1 = 1; p2 = 1; p3 = 0;
     #1 p1 = 1; p2 = 1; p3 = 1;
 end

 initial begin
   #8
   $display("\n");
   $display("A B C | Y");
   $display("------|--");
   $monitor("%b %b %b | %b", p4, p5, p6, out2);
        p4 = 0; p5 = 0; p6 = 0;
     #1 p4 = 0; p5 = 0; p6 = 1;
     #1 p4 = 0; p5 = 1; p6 = 0;
     #1 p4 = 0; p5 = 1; p6 = 1;
     #1 p4 = 1; p5 = 0; p6 = 0;
     #1 p4 = 1; p5 = 0; p6 = 1;
     #1 p4 = 1; p5 = 1; p6 = 0;
     #1 p4 = 1; p5 = 1; p6 = 1;
 end

 initial begin
   #16
   $display("\n");
   $display("A B C | Y");
   $display("------|--");
   $monitor("%b %b %b | %b", p7, p8, p9, out3);
        p7 = 0; p8 = 0; p9 = 0;
     #1 p7 = 0; p8 = 0; p9 = 1;
     #1 p7 = 0; p8 = 1; p9 = 0;
     #1 p7 = 0; p8 = 1; p9 = 1;
     #1 p7 = 1; p8 = 0; p9 = 0;
     #1 p7 = 1; p8 = 0; p9 = 1;
     #1 p7 = 1; p8 = 1; p9 = 0;
     #1 p7 = 1; p8 = 1; p9 = 1;
 end

 initial begin
  #24
  $display("\n");
  $display("A B C | Y");
  $display("------|--");
  $monitor("%b %b %b | %b", p10, p11, p12, out4);
       p10 = 0; p11 = 0; p12 = 0;
    #1 p10 = 0; p11 = 0; p12 = 1;
    #1 p10 = 0; p11 = 1; p12 = 0;
    #1 p10 = 0; p11 = 1; p12 = 1;
    #1 p10 = 1; p11 = 0; p12 = 0;
    #1 p10 = 1; p11 = 0; p12 = 1;
    #1 p10 = 1; p11 = 1; p12 = 0;
    #1 p10 = 1; p11 = 1; p12 = 1;
 end

 initial begin
  #32
  $display("\n");
  $display("A B C | Y");
  $display("------|--");
  $monitor("%b %b %b | %b", p13, p14, p15, out5);
       p13 = 0; p14 = 0; p15 = 0;
    #1 p13 = 0; p14 = 0; p15 = 1;
    #1 p13 = 0; p14 = 1; p15 = 0;
    #1 p13 = 0; p14 = 1; p15 = 1;
    #1 p13 = 1; p14 = 0; p15 = 0;
    #1 p13 = 1; p14 = 0; p15 = 1;
    #1 p13 = 1; p14 = 1; p15 = 0;
    #1 p13 = 1; p14 = 1; p15 = 1;
 end

 initial begin
  #40
  $display("\n");
  $display("A B C | Y");
  $display("------|--");
  $monitor("%b %b %b | %b", p16, p17, p18, out6);
       p16 = 0; p17 = 0; p18 = 0;
    #1 p16 = 0; p17 = 0; p18 = 1;
    #1 p16 = 0; p17 = 1; p18 = 0;
    #1 p16 = 0; p17 = 1; p18 = 1;
    #1 p16 = 1; p17 = 0; p18 = 0;
    #1 p16 = 1; p17 = 0; p18 = 1;
    #1 p16 = 1; p17 = 1; p18 = 0;
    #1 p16 = 1; p17 = 1; p18 = 1;
 end

initial
  #50 $finish;

initial begin
  $dumpfile("Alarma_tb.vcd");
  $dumpvars(0, testbench);
end

endmodule

Laboratorio_04/Ejercicio05/Alarma_tb.vcd
$date
	Fri Aug 07 09:55:07 2020
$end
$version
	Icarus Verilog
$end
$timescale
	1ps
$end
$scope module testbench $end
$var wire 1 ! out6 $end
$var wire 1 " out5 $end
$var wire 1 # out4 $end
$var wire 1 $ out3 $end
$var wire 1 % out2 $end
$var wire 1 & out1 $end
$var reg 1 ' p1 $end
$var reg 1 ( p10 $end
$var reg 1 ) p11 $end
$var reg 1 * p12 $end
$var reg 1 + p13 $end
$var reg 1 , p14 $end
$var reg 1 - p15 $end
$var reg 1 . p16 $end
$var reg 1 / p17 $end
$var reg 1 0 p18 $end
$var reg 1 1 p2 $end
$var reg 1 2 p3 $end
$var reg 1 3 p4 $end
$var reg 1 4 p5 $end
$var reg 1 5 p6 $end
$var reg 1 6 p7 $end
$var reg 1 7 p8 $end
$var reg 1 8 p9 $end
$scope module MK1 $end
$var wire 1 6 A $end
$var wire 1 7 B $end
$var wire 1 8 C $end
$var wire 1 $ Y $end
$upscope $end
$scope module MK2 $end
$var wire 1 . A $end
$var wire 1 / B $end
$var wire 1 0 C $end
$var wire 1 ! Y $end
$var wire 1 9 notA $end
$var wire 1 : notB $end
$upscope $end
$scope module PO1 $end
$var wire 1 3 A $end
$var wire 1 4 B $end
$var wire 1 5 C $end
$var wire 1 % Y $end
$upscope $end
$scope module PO2 $end
$var wire 1 + A $end
$var wire 1 , B $end
$var wire 1 - C $end
$var wire 1 " Y $end
$var wire 1 ; notA $end
$var wire 1 < notB $end
$upscope $end
$scope module SO1 $end
$var wire 1 ' A $end
$var wire 1 1 B $end
$var wire 1 2 C $end
$var wire 1 & Y $end
$upscope $end
$scope module SO2 $end
$var wire 1 ( A $end
$var wire 1 ) B $end
$var wire 1 * C $end
$var wire 1 # Y $end
$var wire 1 = andA $end
$var wire 1 > andB $end
$var wire 1 ? andC $end
$var wire 1 @ andD $end
$var wire 1 A andE $end
$var wire 1 B andF $end
$var wire 1 C andG $end
$var wire 1 D notA $end
$var wire 1 E notB $end
$var wire 1 F notC $end
$upscope $end
$upscope $end
$enddefinitions $end
#0
$dumpvars
xF
xE
xD
xC
xB
xA
x@
x?
x>
x=
x<
x;
x:
x9
x8
x7
x6
x5
x4
x3
02
01
x0
x/
x.
x-
x,
x+
x*
x)
x(
0'
1&
x%
x$
x#
x"
x!
$end
#1
12
#2
02
11
#3
12
#4
02
01
1'
#5
12
#6
0&
02
11
#7
1&
12
#8
1%
05
04
03
#9
15
#10
05
14
#11
15
#12
05
04
13
#13
15
#14
0%
05
14
#15
1%
15
#16
1$
08
07
06
#17
18
#18
08
17
#19
18
#20
08
07
16
#21
18
#22
0$
08
17
#23
1$
18
#24
1#
1>
1=
1F
0?
0@
1E
0A
0B
0C
1D
0*
0)
0(
#25
0=
0F
1*
#26
1?
0>
1F
0E
0*
1)
#27
0?
1@
0F
1*
#28
1A
1F
0@
1E
0D
0*
0)
1(
#29
0A
1B
0F
1*
#30
0#
0B
1F
0E
0*
1)
#31
1#
1C
0F
1*
#32
1"
1<
1;
0-
0,
0+
#33
1-
#34
0<
0-
1,
#35
1-
#36
1<
0;
0-
0,
1+
#37
1-
#38
0"
0<
0-
1,
#39
1"
1-
#40
1!
1:
19
00
0/
0.
#41
10
#42
0:
00
1/
#43
10
#44
1:
09
00
0/
1.
#45
10
#46
0!
0:
00
1/
#47
1!
10
