Laboratorio_03/05.Tabla03 POS/Tabla03POS.v
  module Tabla03POS();

  reg A, B, C, D;
  wire orA, orB, orC, orD, orE, orF, orG, orH, orI, notA, notB, notC, notD, out;

  or O1(orA, A, notB, C, D);
  or O2(orB, A, notB, C, notD);
  or O3(orC, A, notB, notC, D);
  or O4(orD, A, notB, notC, notD);
  or O5(orE, notA, B, C, notD);
  or O6(orF, notA, B, notC, notD);
  or O7(orG, notA, notB, C, D);
  or O8(orH, notA, notB, C, notD);
  or O9(orI, notA, notB, notC, notD);
  and Y1(out, orA, orB, orC, orD, orE, orF, orG, orH, orI);
  not Y1(notA, A);
  not Y2(notB, B);
  not Y3(notC, C);
  not Y4(notD, D);

  initial begin
    $display("A B C D | Y");

    $monitor("%b %b %b %b | %b", A, B, C, D, out);
       A = 0; B = 0; C = 0; D= 0;
    #1 A = 0; B = 0; C = 0; D= 1;
    #1 A = 0; B = 0; C = 1; D= 0;
    #1 A = 0; B = 0; C = 1; D= 1;
    #1 A = 0; B = 1; C = 0; D= 0;
    #1 A = 0; B = 1; C = 0; D= 1;
    #1 A = 0; B = 1; C = 1; D= 0;
    #1 A = 0; B = 1; C = 1; D= 1;
    #1 A = 1; B = 0; C = 0; D= 0;
    #1 A = 1; B = 0; C = 0; D= 1;
    #1 A = 1; B = 0; C = 1; D= 0;
    #1 A = 1; B = 0; C = 1; D= 1;
    #1 A = 1; B = 1; C = 0; D= 0;
    #1 A = 1; B = 1; C = 0; D= 1;
    #1 A = 1; B = 1; C = 1; D= 0;
    #1 A = 1; B = 1; C = 1; D= 1;
    #1 $finish;
  end

  initial
    begin
      $dumpfile("Tabla03POS_tb.vcd");
      $dumpvars(0,Tabla03POS);
    end

endmodule

Laboratorio_03/05.Tabla03 POS/Tabla03POS_tb.vcd
$date
	Fri Jul 31 14:40:50 2020
$end
$version
	Icarus Verilog
$end
$timescale
	1ps
$end
$scope module Tabla03POS $end
$var wire 1 ! notA $end
$var wire 1 " notB $end
$var wire 1 # notC $end
$var wire 1 $ notD $end
$var wire 1 % orA $end
$var wire 1 & orB $end
$var wire 1 ' orC $end
$var wire 1 ( orD $end
$var wire 1 ) orE $end
$var wire 1 * orF $end
$var wire 1 + orG $end
$var wire 1 , orH $end
$var wire 1 - orI $end
$var wire 1 . out $end
$var reg 1 / A $end
$var reg 1 0 B $end
$var reg 1 1 C $end
$var reg 1 2 D $end
$upscope $end
$enddefinitions $end
#0
$dumpvars
02
01
00
0/
1.
1-
1,
1+
1*
1)
1(
1'
1&
1%
1$
1#
1"
1!
$end
#1
0$
12
#2
1$
0#
02
11
#3
0$
12
#4
0.
1$
1#
1&
0%
0"
02
01
10
#5
0.
0&
0$
1%
12
#6
1$
0'
0#
1&
02
11
#7
0.
0(
0$
1'
12
#8
1.
1$
1#
1"
1*
1)
0!
1(
02
01
00
1/
#9
0.
0)
0$
12
#10
1.
1$
0#
1)
02
11
#11
0.
0*
0$
12
#12
1$
1#
1,
0+
0"
1*
02
01
10
#13
0.
0,
0$
1+
12
#14
1.
1$
0#
1,
02
11
#15
0.
0-
0$
12
