Laboratorio_03/07.Tabla04 POS/Tabla04POS.v
  module Tabla04POS();

  reg A, B, C, D;
  wire orA, orB, orC, orD, orE, orF, orG, orH, orI, notA, notB, notC, notD, out;

  or O1(orA, A, B, C, notD);
  or O2(orB, A, notB, C, D);
  or O3(orC, A, notB, C, notD);
  or O4(orD, notA, B, C, notD);
  or O5(orE, notA, B, notC, notD);
  or O6(orF, notA, notB, C, D);
  or O7(orG, notA, notB, C, notD);
  or O8(orH, notA, notB, notC, D);
  or O9(orI, notA, notB, notC, notD);

  and Y1(out, orA, orB, orC, orD, orE, orF, orG, orH, orI);

  not N1(notA, A);
  not N2(notB, B);
  not N3(notC, C);
  not N4(notD, D);

  initial begin
    $display("A B C D | Y");

    $monitor("%b %b %b %b | %b", A, B, C, D, out);
       A = 0; B = 0; C = 0; D= 0;
    #1 A = 0; B = 0; C = 0; D= 1;
    #1 A = 0; B = 0; C = 1; D= 0;
    #1 A = 0; B = 0; C = 1; D= 1;
    #1 A = 0; B = 1; C = 0; D= 0;
    #1 A = 0; B = 1; C = 0; D= 1;
    #1 A = 0; B = 1; C = 1; D= 0;
    #1 A = 0; B = 1; C = 1; D= 1;
    #1 A = 1; B = 0; C = 0; D= 0;
    #1 A = 1; B = 0; C = 0; D= 1;
    #1 A = 1; B = 0; C = 1; D= 0;
    #1 A = 1; B = 0; C = 1; D= 1;
    #1 A = 1; B = 1; C = 0; D= 0;
    #1 A = 1; B = 1; C = 0; D= 1;
    #1 A = 1; B = 1; C = 1; D= 0;
    #1 A = 1; B = 1; C = 1; D= 1;
    #1 $finish;
  end

  initial
    begin
      $dumpfile("Tabla04POS_tb.vcd");
      $dumpvars(0,Tabla04POS);
    end

endmodule

Laboratorio_03/07.Tabla04 POS/Tabla04POS_tb.vcd
$date
	Fri Jul 31 14:42:38 2020
$end
$version
	Icarus Verilog
$end
$timescale
	1ps
$end
$scope module Tabla04POS $end
$var wire 1 ! notA $end
$var wire 1 " notB $end
$var wire 1 # notC $end
$var wire 1 $ notD $end
$var wire 1 % orA $end
$var wire 1 & orB $end
$var wire 1 ' orC $end
$var wire 1 ( orD $end
$var wire 1 ) orE $end
$var wire 1 * orF $end
$var wire 1 + orG $end
$var wire 1 , orH $end
$var wire 1 - orI $end
$var wire 1 . out $end
$var reg 1 / A $end
$var reg 1 0 B $end
$var reg 1 1 C $end
$var reg 1 2 D $end
$upscope $end
$enddefinitions $end
#0
$dumpvars
02
01
00
0/
1.
1-
1,
1+
1*
1)
1(
1'
1&
1%
1$
1#
1"
1!
$end
#1
0.
0%
0$
12
#2
1.
1$
0#
1%
02
11
#3
0$
12
#4
0.
1$
1#
1'
0&
0"
02
01
10
#5
0.
0'
0$
1&
12
#6
1.
1$
0#
1'
02
11
#7
0$
12
#8
1.
1$
1#
1"
1)
1(
0!
02
01
00
1/
#9
0.
0(
0$
12
#10
1.
1$
0#
1(
02
11
#11
0.
0)
0$
12
#12
1$
1#
1+
0*
0"
1)
02
01
10
#13
0.
0+
0$
1*
12
#14
1$
0,
0#
1+
02
11
#15
0.
0-
0$
1,
12
