Laboratorio_03/01.Tabla01 POS/Tabla01POS.v
  module Tabla01POS();

  reg A, B, C;
  wire orA, orB, orC, orD, notA, notB, notC, out;

  or O1(orA, A, B, notC);
  or O2(orB, A, notB, notC);
  or O3(orC, notA, notB, C);
  and Y1(out, orA, orB, orC);
  not N1(notA, A);
  not N2(notB, B);
  not N3(notC, C);

  initial begin
    $display("A B C | Y");

    $monitor("%b %b %b | %b", A, B, C, out);
       A = 0; B = 0; C= 0;
    #1 A = 0; B = 0; C= 1;
    #1 A = 0; B = 1; C= 0;
    #1 A = 0; B = 1; C= 1;
    #1 A = 1; B = 0; C= 0;
    #1 A = 1; B = 0; C= 1;
    #1 A = 1; B = 1; C= 0;
    #1 A = 1; B = 1; C= 1;
    #1 $finish;
  end

  initial
    begin
      $dumpfile("Tabla01POS_tb.vcd");
      $dumpvars(0,Tabla01POS);
    end

endmodule

Laboratorio_03/01.Tabla01 POS/Tabla01POS_tb.vcd
$date
	Fri Jul 31 14:33:35 2020
$end
$version
	Icarus Verilog
$end
$timescale
	1ps
$end
$scope module Tabla01POS $end
$var wire 1 ! notA $end
$var wire 1 " notB $end
$var wire 1 # notC $end
$var wire 1 $ orA $end
$var wire 1 % orB $end
$var wire 1 & orC $end
$var wire 1 ' out $end
$var reg 1 ( A $end
$var reg 1 ) B $end
$var reg 1 * C $end
$upscope $end
$enddefinitions $end
#0
$dumpvars
0*
0)
0(
1'
1&
1%
1$
1#
1"
1!
$end
#1
0'
0$
0#
1*
#2
1'
1#
0"
1$
0*
1)
#3
0'
0%
0#
1*
#4
1'
1#
1"
0!
1%
0*
0)
1(
#5
0#
1*
#6
0'
1#
0&
0"
0*
1)
#7
1'
0#
1&
1*
