Laboratorio_03/03.Tabla02 POS/Tabla02POS.v
  module Tabla02POS();

  reg A, B, C;
  wire orA, orB, orC, orD, orE, notA, notB, notC, out;

  or O1(orA, A, B, C);
  or O2(orB, A, notB, C);
  or O3(orC, A, notB, notC);
  or O4(orD, notA, B, C);
  or O5(orE, notA, B, notC);
  and Y1(out, orA, orB, orC, orD, orE);
  not Y1(notA, A);
  not Y2(notB, B);
  not Y3(notC, C);

  initial begin
    $display("A B C | Y");

    $monitor("%b %b %b | %b", A, B, C, out);
       A = 0; B = 0; C= 0;
    #1 A = 0; B = 0; C= 1;
    #1 A = 0; B = 1; C= 0;
    #1 A = 0; B = 1; C= 1;
    #1 A = 1; B = 0; C= 0;
    #1 A = 1; B = 0; C= 1;
    #1 A = 1; B = 1; C= 0;
    #1 A = 1; B = 1; C= 1;
    #1 $finish;
  end

  initial
    begin
      $dumpfile("Tabla02POS_tb.vcd");
      $dumpvars(0,Tabla02POS);
    end

endmodule

Laboratorio_03/03.Tabla02 POS/Tabla02POS_tb.vcd
$date
	Fri Jul 31 14:38:56 2020
$end
$version
	Icarus Verilog
$end
$timescale
	1ps
$end
$scope module Tabla02POS $end
$var wire 1 ! notA $end
$var wire 1 " notB $end
$var wire 1 # notC $end
$var wire 1 $ orA $end
$var wire 1 % orB $end
$var wire 1 & orC $end
$var wire 1 ' orD $end
$var wire 1 ( orE $end
$var wire 1 ) out $end
$var reg 1 * A $end
$var reg 1 + B $end
$var reg 1 , C $end
$upscope $end
$enddefinitions $end
#0
$dumpvars
0,
0+
0*
0)
1(
1'
1&
1%
0$
1#
1"
1!
$end
#1
1)
0#
1$
1,
#2
0)
1#
0%
0"
0,
1+
#3
0)
0&
0#
1%
1,
#4
1#
1"
1(
0'
0!
1&
0,
0+
1*
#5
0)
0(
0#
1'
1,
#6
1)
1#
0"
1(
0,
1+
#7
0#
1,
